{
  "$schema": "https://schema.management.azure.com/schemas/2019-04-01/deploymentParameters.json#",
  "contentVersion": "1.0.0.0",
  "parameters": {
    "environment": {
      "value": "dev"
    },
    "location": {
      "value": "eastus"
    },
    "baseName": {
      "value": "pricewatch"
    },
    "githubRepo": {
      "value": "YOUR_GITHUB_USERNAME/price-tracker"
    },
    "b2cTenantName": {
      "value": "YOUR_B2C_TENANT_NAME"
    },
    "b2cClientId": {
      "value": "YOUR_B2C_CLIENT_ID"
    }
  }
}
